rctf/__init__.py
rctf/config.py
rctf/logger.py
rctf/rctf.py
rctf-1.0.data/scripts/rctf
rctf-1.0.data/scripts/rctf.sh
rctf-cli/rctf/__init__.py
rctf-cli/rctf/config.py
rctf-cli/rctf/logger.py
rctf-cli/rctf/rctf.py
rctf-1.0.dist-info/LICENSE
rctf-1.0.dist-info/METADATA
rctf-1.0.dist-info/WHEEL
rctf-1.0.dist-info/top_level.txt
rctf-1.0.dist-info/RECORD
