Metadata-Version: 2.1
Name: rctf
Version: 1.0
Summary: A CLI tool for managing your rCTF installation
Home-page: http://rctf.redpwn.net/
Author: Aaron Esau
Author-email: redpwn@aaronesau.com
License: BSD-3-Clause
Platform: UNKNOWN
Requires-Python: >=3.6
Requires-Dist: requests
Requires-Dist: envparse
